alloy/__init__.py
alloy/api/__init__.py
alloy-0.3a0.dist-info/WHEEL
alloy-0.3a0.dist-info/METADATA
alloy-0.3a0.dist-info/RECORD
