Metadata-Version: 2.4
Name: alloy
Version: 0.3a0
Summary: High-performance runtime
Author: Sam Gammon
Author-email: Sam Gammon <sam@elide.dev>
License-Expression: MIT
Classifier: Programming Language :: Python :: 3
Classifier: Operating System :: OS Independent
Requires-Dist: lazy-loader
Requires-Python: >=3.11
